README.md
setup.py
src/ipey/__init__.py
src/ipey.egg-info/PKG-INFO
src/ipey.egg-info/SOURCES.txt
src/ipey.egg-info/dependency_links.txt
src/ipey.egg-info/top_level.txt
src/ipey/document/__init__.py
src/ipey/document/document.py
src/ipey/document/page.py
src/ipey/document/reader.py
src/ipey/document/writer.py
src/ipey/helper/__init__.py
src/ipey/helper/helper.py
src/ipey/primitive/__init__.py
src/ipey/primitive/arc.py
src/ipey/primitive/circle.py
src/ipey/primitive/ellipse.py
src/ipey/primitive/glyph.py
src/ipey/primitive/group.py
src/ipey/primitive/label.py
src/ipey/primitive/line.py
src/ipey/primitive/minipage.py
src/ipey/primitive/polygon.py
src/ipey/primitive/primitive.py
src/ipey/primitive/rectangle.py
src/ipey/primitive/spline.py
src/ipey/primitive/splinegon.py
src/ipey/static/__init__.py
src/ipey/static/basic.xml
src/ipey/static/settings.ini