Metadata-Version: 2.1
Name: ipey
Version: 0.0.12
Summary: Create IPE drawings in python.
Home-page: UNKNOWN
Author: Markus Wallinger
License: MIT
Platform: UNKNOWN
Classifier: Programming Language :: Python :: 3
Classifier: License :: OSI Approved :: MIT License
Classifier: Operating System :: OS Independent
Requires-Python: >=3.6
